colppy/__init__.py
colppy/cli/__init__.py
colppy/cli/main.py
colppy/helpers/__init__.py
colppy/helpers/data_frames.py
colppy/helpers/date.py
colppy/helpers/errors.py
colppy/helpers/formatters.py
colppy/helpers/logger.py
colppy/models/__init__.py
colppy/models/auth.py
colppy/models/clientes.py
colppy/models/cobro_factura.py
colppy/models/compras_pago_details.py
colppy/models/comprobante_compra_details.py
colppy/models/comprobante_venta_details.py
colppy/models/comprobantes_compra.py
colppy/models/comprobantes_venta.py
colppy/models/empresas.py
colppy/models/movimientos.py
colppy/models/proveedores.py
colppy/operations/__init__.py
colppy/operations/config.py
colppy/operations/main.py
colppy/request/__init__.py
colppy/request/clientes_request.py
colppy/request/comprobante_compra_details_request.py
colppy/request/comprobante_venta_details_request.py
colppy/request/comprobantes_compra_request.py
colppy/request/comprobantes_venta_request.py
colppy/request/empresas_request.py
colppy/request/movimientos_request.py
colppy/request/proveedores_request.py
colppy/request/request.py
colppy/response/__init__.py
colppy/response/clientes_response.py
colppy/response/compras_pago_details_response.py
colppy/response/comprobante_compra_details_response.py
colppy/response/comprobante_venta_details_response.py
colppy/response/comprobantes_compra_response.py
colppy/response/comprobantes_venta_response.py
colppy/response/empresas_response.py
colppy/response/movimientos_response.py
colppy/response/proveedores_response.py
colppy/response/response.py
colppy_api-1.2.2.dist-info/METADATA
colppy_api-1.2.2.dist-info/WHEEL
colppy_api-1.2.2.dist-info/entry_points.txt
colppy_api-1.2.2.dist-info/RECORD
