Metadata-Version: 2.4
Name: colppy-api
Version: 1.2.2
Summary: Cliente API para Colppy (NO OFICIAL)
Project-URL: Homepage, https://bitbucket.org/groovinads/colppi-api
Project-URL: Issues, https://bitbucket.org/groovinads/colppi-api/issues
Author-email: Groovinads <juanmanuel.panozzo@groovinads.com>
License: MIT
Keywords: api,client,colppy
Classifier: Operating System :: OS Independent
Classifier: Programming Language :: Python :: 3
Classifier: Programming Language :: Python :: 3.11
Requires-Python: >=3.10
Requires-Dist: click>=8.1.3
Requires-Dist: colorama>=0.4.6
Requires-Dist: httpx>=0.24.0
Requires-Dist: pandas>=2.0.0
Requires-Dist: python-dateutil>=2.8.2
